{
	"data": {
		"notes": [
			{
				"user": {
					"image": "https://img.xiaohongshu.com/avatar/586e4c3402f37d4fc20c28a7.jpg@80w_80h_90q_1e_1c_1x.jpg",
					"userid": "56b878c5b8ce1a326662416a",
					"discoverys_total": 84,
					"nickname": "阿默的日常",
					"id": "56b878c5b8ce1a326662416a",
					"fans_total": 417
				},
				"title": "arouge抗过敏晚安睡眠面膜",
				"image": "http://ci.xiaohongshu.com/5b552bca-bb94-47f8-8750-fdfd03de1a8e@r_240w_240h.jpg",
				"collect": 227,
				"related_goods_name": "",
				"image_b": "http://ci.xiaohongshu.com/5b552bca-bb94-47f8-8750-fdfd03de1a8e@r_1280w_1280h.jpg",
				"likes": 86,
				"id": "58d2530678362377f292c03c",
				"desc": "arouge是日本的小众药妆品牌，真的是太惊艳了。\n刚收到看着35ml，我以为发错了，对过标签的确是面膜😂😂😂，太mini了，然后膏体是黄色的，像布丁一样QQ的，很舒服。\n洁面后，正常护肤结束最后一步，涂这个，用量很省，延展性非常好，然后神器的事情来了，大概五六分钟，他就完全吸收了，脸上基本上就涂完面霜那种感觉，毫无负担啊。简直让我对睡眠面膜大改观，完全不怕脸黏糊糊的。大概十分钟后带眼罩也没问题。\n第二天早上起来脸润润的，而且我最近有点过敏，下巴上很多小疙瘩，感觉第二天好很多。\n😅说好起码过半再发文，但是这个我实在忍不住。太喜欢了，❤❤❤❤❤\n还有款美白的，哈哈哈，已经下单了，好期待#干皮最爱补水面膜"
			}, {
				"user": {
					"image": "https://img.xiaohongshu.com/avatar/58d27256e9521a08a74eed17.jpg@80w_80h_90q_1e_1c_1x.jpg",
					"userid": "5804d71d50c4b46219b83906",
					"discoverys_total": 3,
					"nickname": "婉婉呦_",
					"id": "5804d71d50c4b46219b83906",
					"fans_total": 75
				},
				"title": "超级敏感肌用的水",
				"image": "http://ci.xiaohongshu.com/c0aa891b-1baf-4eb0-b577-27f0cf5b1b53@r_240w_240h.jpg",
				"collect": 146,
				"related_goods_name": "浓稠补水不黏腻",
				"image_b": "http://ci.xiaohongshu.com/c0aa891b-1baf-4eb0-b577-27f0cf5b1b53@r_1280w_1280h.jpg",
				"likes": 50,
				"id": "58d251aa14de4117fd0aa356",
				"desc": "相信我用的爽肤水大家也都po过了的，有没有人和我一样是超级敏感肌，突然就会状态很糟糕，泛红。这个时候湿敷也很重要\n蕙仁水 我一般是化妆前使用的，大多数人的皮肤都适合用这款水，再给别人化妆前我也是用的这一款 平价 而且一罐这么大也可以用好久\n推荐指数🌟🌟🌟🌟\n科颜氏高保湿水 我只用了几次，本来买之前我也做了功课，但是我涂抹在脸上还会有刺激性的感觉，我也不确定是不是因为我的皮肤太干燥了，但是保湿的效果是很好的\n推荐指数🌟🌟🌟\nsuisse 这个牌子应该算比较冷门的，但是并不输过热门产品，皮肤会觉得滑滑的，不刺激我最近都在使用\n推荐指数🌟🌟🌟🌟🌟\nNatio 我用第二瓶了，皮肤干燥的话敷了会很刺激但是是可以接受的那种，不缺水情况下敷就是挺舒服的，湿敷比较有效果，保湿效果明显，直接打的话打三四次也会皮肤滑滑的\n推荐指数🌟🌟🌟\n诚野医生 几乎人手一瓶吧，镇静效果真的不是吹，我有时候脸颊泛红湿敷之后就不会了，会一直回购\n推荐指数🌟🌟🌟🌟🌟\n暂时用的就是这几款水啦，每一次用新产品也是要做好工课才试，毕竟没办法忍受的皮肤状态，好的时候又特别好。"
			}, {
				"user": {
					"image": "https://img.xiaohongshu.com/avatar/58b6d31be9521a403262442c.jpg@80w_80h_90q_1e_1c_1x.jpg",
					"userid": "542ffd60d6e4a9413cc451a4",
					"discoverys_total": 238,
					"nickname": "向小飞猪看齐",
					"id": "542ffd60d6e4a9413cc451a4",
					"fans_total": 2297
				},
				"title": "你听说过“水光眼”吗？？？（8款眼霜测评）",
				"image": "http://ci.xiaohongshu.com/3aee0806-c9fe-4713-ba3e-779b4528f9a2@r_240w_240h.jpg",
				"collect": 140,
				"related_goods_name": "英国王妃御用面膜",
				"image_b": "http://ci.xiaohongshu.com/3aee0806-c9fe-4713-ba3e-779b4528f9a2@r_1280w_1280h_w2.jpg",
				"likes": 65,
				"id": "58d23d62a9b2ed3c729e833c",
				"desc": "皱纹是岁月的痕迹，我们很难留住时间，却可以冻龄我们的皮肤。女性皮肤往往比男性更容易出现皱纹，所以补"
			}, {
				"user": {
					"image": "https://img.xiaohongshu.com/avatar/57a1c183e9521a72780dbdc9.jpg@80w_80h_90q_1e_1c_1x.jpg",
					"userid": "5594a6665894464be38ce6ed",
					"discoverys_total": 135,
					"nickname": "美妆薯",
					"id": "5594a6665894464be38ce6ed",
					"fans_total": 178666
				},
				"title": "听说这些超好用的护肤品100块都不到，贵妇牌吓得瑟瑟发抖",
				"image": "http://ci.xiaohongshu.com/662ba4ee-360e-43f1-8f6d-7eafabbb3908@r_240w_240h.jpg",
				"collect": 5430,
				"related_goods_name": "消灭姨妈熬夜痘",
				"image_b": "http://ci.xiaohongshu.com/662ba4ee-360e-43f1-8f6d-7eafabbb3908@r_1280w_1280h_w2.jpg",
				"likes": 1035,
				"id": "58d26cd7346094163867165b",
				"desc": "我们常常听别人说：“没钱还护肤？”或者说：“学生党用清水洗洗脸就好了。”似乎护肤就一定要跟花很多钱"
			}, {
				"user": {
					"image": "https://img.xiaohongshu.com/avatar/554c991eb4c4d6080c662c4c.jpg@80w_80h_90q_1e_1c_1x.jpg",
					"userid": "554b47bb4fac6302b1ef57bf",
					"discoverys_total": 64,
					"nickname": "Sophie蘇小妹",
					"id": "554b47bb4fac6302b1ef57bf",
					"fans_total": 162
				},
				"title": "小花轉新裝-蘇菲娜芯美顏高保濕防晒霜",
				"image": "http://ci.xiaohongshu.com/86331aa0-532a-430b-ba0e-aa83fa06b023@r_240w_240h.jpg",
				"collect": 25,
				"related_goods_name": "清透防晒上脸自然",
				"image_b": "http://ci.xiaohongshu.com/86331aa0-532a-430b-ba0e-aa83fa06b023@r_1280w_1280h.jpg",
				"likes": 24,
				"id": "58d21924d2c8a52d8c0216b3",
				"desc": "第一枝小藍花是朋友靚太送給的的生日禮物。用過了許多臉部防晒，最好的還是Sofina! 要皮膚白還是要選日系的防晒，原因只有中國跟日本女性愛一白遮三醜，女漢子如小妹什麼都不擦、都一定要擦防曬出門。森山系工作，防曬是每天例行工事。\n見快要用完了，去年11月左右到日本旅行便帶了2枝全新的Sofina Beaute系列回來。一枝小藍花、一枝美白的小白花。打算春天用小藍花、夏天用小白花。\n新的Beaute系列的所有產品都加有iTPS複合体成份，夜來香之花瓣提煉出來，令用後更保濕。顧客對象是30到50歲的年齡層。（50歲以上是Grace 系列）\n今天終於用完了舊小花，可以開新小花了！新版的小藍花（Sofina Beaute ) 仍然是藍色包裝，打開盒子透明的藍色令人感到很清爽。有清爽型及滋潤型。清爽型新裝和舊版的瓶子大同小異，滋潤型包裝有點像牙膏。這次買了滋潤型，質地比清爽型有點濃，但仍然清爽易推。混合性皮膚，擦了到了晚上比之前的舊版清爽型有改善，額頭出油比以前少（是少不時沒有哦！）。但總的來說，這是最好用的防晒。\n圖1:舊款空瓶與新款小藍花\n圖2:新款小藍花前\n圖3:新款小藍花後\n#春季防晒必备\n#清爽不黏腻的防晒霜\n#空瓶记"
			}, {
				"user": {
					"image": "https://img.xiaohongshu.com/avatar/58a4f45f02f37d5070e69e54.jpg@80w_80h_90q_1e_1c_1x.jpg",
					"userid": "575a84a050c4b42d541373b5",
					"discoverys_total": 3,
					"nickname": "G41L",
					"id": "575a84a050c4b42d541373b5",
					"fans_total": 65
				},
				"title": "几款补水美白面膜使用体验～",
				"image": "http://ci.xiaohongshu.com/ee5f092b-aba9-44c9-b825-25b3a601b613@r_240w_240h.jpg",
				"collect": 2,
				"related_goods_name": "补水修复镇静舒缓",
				"image_b": "http://ci.xiaohongshu.com/ee5f092b-aba9-44c9-b825-25b3a601b613@r_1280w_1280h.jpg",
				"likes": 4,
				"id": "58c2b0c7d5945f15e5fc1e53",
				"desc": "我是混油偏干性肌肤 角质层薄 有几粒斑 两颊不注意就会起皮\n说到补水美白不得不推荐dior水动力系列的护肤品\n尤其是这款水动力睡眠面膜 用完以后第二天皮肤都水汪汪的\n补水能力是外面那些妖艳贱货难以匹敌的💪\n一个星期用一次就可以\n而那个一粒一粒的胶囊面膜是在皮肤状态很缺水的时候才会用到的\n一盒有7粒 要连用7天 一天一粒（怎么跟服药似的😂）\n用完以后一捏就能掐出水来😌（对！dior的面膜不仅用的时候感觉良好，重点是，用完后几天内皮肤都水嫩得不行！）\n这两款面膜 我都是敷个十几分钟就会洗掉的 不建议带着睡觉\n然后是很火的彼得罗夫\n价格比dior便宜 所谓一分价一分货\n补水效果自然也没有dior那么好\n主要是 用完后第二天皮肤就会干掉 说明补水没有真的补进去\n所以这个我拿来一天一敷 每天晚上都会用\n然后第二天再用高丝的大面包膜 哦 不 大包面膜（有点饿了😋）30回分的\n每天早上用五分钟\n不过目前我只试验了一个月 皮肤确实变白了 斑也淡了 但不知道天天这样有没有副作用 我还在探索中 大家也要看自己的皮肤状态再决定\n接着是雪花秀的撕拉面膜\n一开始是拿来去黑头的\n结果 呵呵 压根没用🙄\n氮素！我发现它可以祛黄气🤗\n我t区油 导致t区肤色比较黄\n用完它以后 t区的颜色会白一点 均匀肤色\n一两个星期一次 不能经常撕拉皮肤 对皮肤不好✋\n最后是倩碧的美白淡斑面膜\n的确有点美白效果 但是对角质层薄的人比较刺激\n皮厚的人放心大胆使吧 我一般用在t区\n剩下的一个面膜我就是凑凑数的 不用它用任何面膜都可以替代\n以上的面膜除了dior的还会继续回购 其余的不会再回购了"
			}, {
				"user": {
					"image": "https://img.xiaohongshu.com/avatar/58c6be6402f37d24d8a4132c.jpg@80w_80h_90q_1e_1c_1x.jpg",
					"userid": "56123e4d33f60c749cbcdc10",
					"discoverys_total": 16,
					"nickname": "万千少女的梦",
					"id": "56123e4d33f60c749cbcdc10",
					"fans_total": 337
				},
				"title": "推荐一支祛痘神器！",
				"image": "http://ci.xiaohongshu.com/a65ceaef-022f-4e71-8203-01eade58d9aa@r_240w_240h.jpg",
				"collect": 39,
				"related_goods_name": "祛痘必不可缺",
				"image_b": "http://ci.xiaohongshu.com/a65ceaef-022f-4e71-8203-01eade58d9aa@r_1280w_1280h.jpg",
				"likes": 16,
				"id": "58cbb47fb46c5d70441cfd29",
				"desc": "[萌萌哒R]先说说的我肤质吧…敏感干皮，角质层薄不耐受，刷酸是想都不要想，一般不会大面积爆痘，来姨妈之前皮肤会不稳定容易长痘，偏偏痘痘还喜欢长在眉心嘴角[扶墙R]偶尔会长闭口，一直在找一种安全祛痘去痘印的产品。#皮肤急救神器\n尝试过狮王 LION 祛痘膏、#石泽研究所澳柯浓茶树精油凝霜、#赛贝格VC粉，对祛痘去痘印和闭口没有任何作用…特别鸡肋…[扶墙R]\n终于！等到了#宝拉珍选￼壬二酸净颜精华！刚好在大姨妈爆痘期间到手开始使用，真的是我的救命稻草！对痘痘闭口都有卓越效果。使用感本身挺温和的，消炎也行。\n😎刚刚发红冒出黄色尖尖的痘痘，连续涂抹三天直接瘪了下去连印都没有！😍😍😍我还尝试涂在嘴角的旧痘印上…竟然也可以淡化痘印！！一些脸上莫名其妙冒出来的小红点都能彻底解决~厉害的我的壬二！[色色R][赞R]\n壬二酸精华里面含有水杨酸，乳液质地，闻着有股淡淡的酸味，（孕妇不能用噢！我是局部长痘，脸颊不长，所以没有大面积使用只是点涂…哪里长痘点哪里~毕竟敏感薄皮还是不要轻易作死…[笑哭R]\n总之这款是集祛痘！祛痘印！去闭口一身的神器！绝对无限回购😉😘\n#我的护肤日常#换季护肤全靠TA"
			}, {
				"user": {
					"image": "https://img.xiaohongshu.com/avatar/58783f9fe9521a1c7f29c0fe.jpg@80w_80h_90q_1e_1c_1x.jpg",
					"userid": "54dc2797e779896174e228da",
					"discoverys_total": 259,
					"nickname": "来不及女王👑",
					"id": "54dc2797e779896174e228da",
					"fans_total": 14082
				},
				"title": "💄素颜必备水红色💄",
				"image": "http://ci.xiaohongshu.com/5324cb4f-ea24-4aae-8c7b-6371327a348e@r_240w_240h.jpg",
				"collect": 292,
				"related_goods_name": "",
				"image_b": "http://ci.xiaohongshu.com/5324cb4f-ea24-4aae-8c7b-6371327a348e@r_1280w_1280h.jpg",
				"likes": 129,
				"id": "58ce6e9014de416c3fc5d0a0",
				"desc": "CHICCA新版唇膏，忘了是13年还是14年出的，新版的唇膏壳牢牢揪住了颜狗的心，就这么控制不住记几，刚出就买下了06。白色钢琴烤漆的质感，全身泛着低调的珠光，没有尖锐的棱角，盖子的logo旁边镶着一颗闪亮的水钻，唇膏拿在手里整体的质感特别好，非常高级。\n当我纯素颜的时候，当我画了裸妆气色不好的时候，都是它解决了我的燃眉之急！！！这是最正统的水红色！水土不服就服它！\n手臂试色左边涂抹多次，右边一次的效果，抹开就有水水的透明感。真嘴试色因为今天下雨，而且已经是傍晚所以拍出来不够高清，但还是能看出来效果。\n买了这么多口红，这支使用频率最高～非常实用！不光是因为水红色百搭提气色，更重要的是它非常滋润，能秒杀我手上一切日常用的润唇膏！嘴巴干裂起皮都可以用它，并且也修复的比润唇膏更好更快。什么你还没有chicca？还不赶紧纳入后宫！！！\n#CHICCA#裸妆最爱的水红色唇膏#直男最爱的唇膏#黄皮最爱的口红#春夏最爱的清新口红#斩男色口红大搜查#我的彩妆测评#颜值爆表的梦幻彩妆"
			}, {
				"user": {
					"image": "https://img.xiaohongshu.com/avatar/58c0e9f902f37d467974db42.jpg@80w_80h_90q_1e_1c_1x.jpg",
					"userid": "5593b424c2bdeb3cb2d589d0",
					"discoverys_total": 281,
					"nickname": "馨儿薇安_",
					"id": "5593b424c2bdeb3cb2d589d0",
					"fans_total": 2263
				},
				"title": "摸着良心推荐·素颜神器",
				"image": "http://ci.xiaohongshu.com/8a4c531d-7a0c-4f86-b625-3f6b7a12d473@r_240w_240h.jpg",
				"collect": 103,
				"related_goods_name": "清新伪素颜",
				"image_b": "http://ci.xiaohongshu.com/8a4c531d-7a0c-4f86-b625-3f6b7a12d473@r_1280w_1280h.jpg",
				"likes": 109,
				"id": "58d1fa8cd2c8a52dc00216b2",
				"desc": "芭妮兰素颜霜，全称芭妮兰梦幻婚礼幻亮霜～\n近期发现的素颜神器！[吧唧R]懒人必备款！\n包装：颜狗🐶被包装折服了，因为蕾丝的外壳真是好看到炸裂！！银白相间真的太少女了！！\n使用感：丝滑！触感很棒！[赞R]\n干皮妆前大救星！！！不会跟底妆搓泥，不会卡粉，不会拔干！！超级润，又好推开，不会油腻！[吧唧R]\n干皮妆前或者素颜出门必备！[得意R]\n妆效：不要指望它美白，这款基本没有什么润色的功能，但是可以很好的提亮，散发出BlingBling的光彩～\n妆后可以用来做高光，妆前用来做隔离乳，帮助底妆不翘皮！[吧唧R]\n毕竟底妆还是需要专门的彩妆产品的呀，这一款，能修饰素颜，就已经敲棒啦～\n这款购于国内专柜，¥228打八折，也是划算的～\n（伸手党能不能仔细看看描述或者图片呢？购买地与价格都标明啦，不要再一遍遍问哪里买的啦～）\n#素颜霜真的好用吗\n芭妮兰 BANILA CO 梦幻婚礼提亮保湿素颜霜"
			}, {
				"user": {
					"image": "http://img.xiaohongshu.com/avatar/5750d86702f37d6ebb83cf04.jpg@120w_120h_92q_1e_1c_1x.jpg",
					"userid": "5650129f484fb6599b396404",
					"discoverys_total": 148,
					"likes": 5593,
					"nickname": "巴拉巴拉种草机",
					"id": "5650129f484fb6599b396404",
					"fans_total": 1389
				},
				"title": "冬天必备的滋润",
				"image": "http://ci.xiaohongshu.com/2852689a-360b-4786-8247-7cd3269f904b@r_240w_240h.jpg",
				"collect": 3,
				"related_goods_name": "",
				"image_b": "http://ci.xiaohongshu.com/2852689a-360b-4786-8247-7cd3269f904b@r_1280w_1280h.jpg",
				"likes": 3,
				"id": "58d1dc4c14de4172360aa356",
				"desc": "这两样东西是我今年发现过冬的法宝，身体和擦手用，特别是安安皲裂膏，全家族人几年前就一直在用了。\n以前我一直很瞧不起安安，觉得这个牌子能有什么好货，我外婆的脚跟每年冬天都会爆裂出血，都是擦这个好的，全家族的女性主妇手都不能没有它。这个是佛山产的，专供北方，超市还有网上都好像不好买，每年我佛山的姨姨为家族买两三盒，每个六瓶，一下子都被瓜分完了。我每晚睡觉前都会涂一层，午觉也会涂一层，白天要看记不记得涂。冬天我无论洗什么都会戴手套，除了洗澡洗脸[偷笑R]，一个冬天，我的手都没长倒刺，很细滑。从此，它就是我的床头必备了。\n还有一样东西，俄罗纳英H软膏，这个应该算是药用产品了。买了好久，真心不知道拿它来干什么，用途很多，但是心理感觉应该是很中庸，效果不大那种吧。冬天很多时候我都爱擦两层身体润肤，一层油，一层乳。那会刚好用完了乳，我就拿着已经过期的俄罗纳英（你没听错，被我放过期了才涂[石化]）将就着涂第二层了，用量很大，因为我想快点用完它[腹黑]。质地很稠很稠，需要把他揉开，但是很滋润。\n用了几天，我滴神啊，之前因为湿疹被我抓伤后又好了的皮肤，龟皮肤色不均的好多地方全部变得好细腻，然后那一块块的皮肤死皮有脱落的趋势。然后我继续用了几天，那些死皮龟皮部分全部脱落了，变成正常的皮肤，但好了以后我就没有继续用了，想着药用的东西还是不要作为日常润肤乳比较好。\n这两样都非常的棒！我想，我遇到了神赐之物！[得意][喜欢]以后成打的囤！逢干皮必推荐！"
			}, {
				"user": {
					"image": "https://img.xiaohongshu.com/avatar/5807a535e9521a4172a494c3.jpg@80w_80h_90q_1e_1c_1x.jpg",
					"userid": "564e7eebe58d1304bdff950d",
					"discoverys_total": 11,
					"nickname": "A1MEEe",
					"id": "564e7eebe58d1304bdff950d",
					"fans_total": 11
				},
				"title": "馥蕾诗玫瑰深度保湿精华",
				"image": "http://ci.xiaohongshu.com/efc0fe91-0464-4c3f-909d-ce156e99f8d0@r_240w_240h.jpg",
				"collect": 22,
				"related_goods_name": "给皮肤一场及时雨",
				"image_b": "http://ci.xiaohongshu.com/efc0fe91-0464-4c3f-909d-ce156e99f8d0@r_1280w_1280h.jpg",
				"likes": 20,
				"id": "58d13156d1d3b91d423ce21f",
				"desc": "作为一枚干敏薄皮 除了补水保湿不过敏真的没有别的要求了\n一直很种草馥蕾诗家的东西 感觉就很天然\n这款精华味道就是酸酸的 很像玫瑰花泡水之后那种味道 开始不喜欢 用着就适应了\n方法🎀挤2～3泵 点涂于脸部 轻揉至吸收 再将掌心搓热捂脸 后续涂面霜\n心得🎀用了一个月了 补水效果还是蛮明显的 脸摸起来也软软的 不知道是不是脸喝饱水的关系 粉刺闭口也有在减少\n[害羞R]专柜价格还是挺友好的 再没有找到更好的补水精华之前 应该会继续回购的"
			}, {
				"user": {
					"image": "https://img.xiaohongshu.com/avatar/06adfd8077d24cc6e7947a2e0bd028bc.png@80w_80h_90q_1e_1c_1x.jpg",
					"userid": "571a2484aed7581c0f49bc04",
					"discoverys_total": 3,
					"nickname": "Cherrylulu_571A7E95",
					"id": "571a2484aed7581c0f49bc04",
					"fans_total": 1
				},
				"image": "http://ci.xiaohongshu.com/efb5214f-c9a1-4988-9417-d4062cd2c696@r_240w_240h.jpg",
				"collect": 2,
				"related_goods_name": "肌肤有它就安心",
				"image_b": "http://ci.xiaohongshu.com/efb5214f-c9a1-4988-9417-d4062cd2c696@r_1280w_1280h.jpg",
				"likes": 1,
				"id": "58d13a51783623308692c03c",
				"desc": "三款网红水🈳️瓶～\n本人痘痘肌干皮（屏障受损） 坐标：杭州\n先入的健康水，确实好用！肥皂水味闻上去很清爽，祛痘很有效！痘痘肌一定要入！痘痘特别严重的时候帮了大忙，这是回购的第二瓶，不过第二瓶用着就没那么惊喜了诶～☺\n一开始用菌菇水味道我不太喜欢，中草药味？质地是三款水中最稠的，夏天的时候入的但是我皮肤偏干用着不会感觉黏腻。这款网上风评不一，但对于我来说却是三款最有效的！便宜大碗，无限回购！😍\n紫苏水的瓶子真的很美（原谅我技术不佳拍不出）味道也是最好闻的，但是可能是我入的时节不对？冬天用的感觉比较鸡肋，暂时不会回购了。😛"
			}, {
				"user": {
					"image": "https://img.xiaohongshu.com/avatar/588a004ee9521a66d9346a01.jpg@80w_80h_90q_1e_1c_1x.jpg",
					"userid": "5583a933b7ba226abfd11aa5",
					"discoverys_total": 15,
					"nickname": "胡胖纸17",
					"id": "5583a933b7ba226abfd11aa5",
					"fans_total": 25
				},
				"title": "平价版健康水面膜 肌美精面膜",
				"image": "http://ci.xiaohongshu.com/0a8cd2f4-fb01-4bb8-abb2-364907dbd209@r_240w_240h.jpg",
				"collect": 33,
				"related_goods_name": "一片痘痘清干净",
				"image_b": "http://ci.xiaohongshu.com/0a8cd2f4-fb01-4bb8-abb2-364907dbd209@r_1280w_1280h.jpg",
				"likes": 25,
				"id": "58d14384faa0524172ae6254",
				"desc": "作为个痘痘星人超爱健康水面膜，然而，作为个一天不敷面膜就会死的人，天天敷健康水面膜真心是太贵了，谁让穷呢！😂\n超级多人不喜欢健康水面膜，觉得就是水，好像没什么精华液，面膜纸也不饱满，可就是这样才适合痘痘肌天天敷那！\n竟然健康水天天敷敷不起，就只好找找替代品了。\n肌美精绿茶面膜，肌美精大人面膜，算下来也就140日元左右一片，这才是可以天天敷的起的价格嘛😂，然而效果完全不输健康水，敷了之后痘痘很明显扁下去，每天敷着敷着，都不怎么冒痘了。\n也是和健康水一样的材质和性质，只是水水的，并没有精华液的感觉，就是这样才可以天天无负担的敷起来啊！\n绿色的是绿茶的，单纯镇静祛痘，白色款，带去痘印和美白功效，但是使用感没大差，我都是抽到哪个用哪个。\n默默的用完囤货，感觉又要买起来了😂"
			}, {
				"user": {
					"image": "https://img.xiaohongshu.com/avatar/584a6884e9521a6a84b8c5f6.jpg@80w_80h_90q_1e_1c_1x.jpg",
					"userid": "584955fa34609433a7a70ede",
					"discoverys_total": 34,
					"nickname": "甜开心心心",
					"id": "584955fa34609433a7a70ede",
					"fans_total": 556
				},
				"title": "🎀被Bobbi Brown家的面霜惊艳到👍🏼",
				"image": "http://ci.xiaohongshu.com/cfba01f6-28a3-4b4b-88f9-7626854598d1@r_240w_240h.jpg",
				"collect": 172,
				"related_goods_name": "乳化干净毛孔清透",
				"image_b": "http://ci.xiaohongshu.com/cfba01f6-28a3-4b4b-88f9-7626854598d1@r_1280w_1280h.jpg",
				"likes": 91,
				"id": "58d1c4bf14de410a8e0aa357",
				"desc": "👏🏼不得不说甩了很多护肤品起家的牌子几条街……\n(之前也有分享一篇BB家美妆产品的笔记，有好货，也有鸡肋，有兴趣的小伙伴可以点击去看看😉)\n💡自己是干皮，就是那种洁面后不涂任何产品立刻干的皮肤。同时不能持续一直只用同一个牌子同一件产品，尤其是护肤品。保湿面霜一罐用完基本上就得换另外个牌子或者系列。\n🎀之前有入Darphin的保湿面霜(有笔记分享哟) ，现在早晚都在用Bobbi Brown家的hydrating cream，用了大概半个月，来说说效果👏🏼👏🏼👏🏼\n👌🏼不用加精油，直接上脸，质地相对厚款面霜轻薄，会比gel着哩的偏厚，但是完全不油腻，并且涂完之后会觉得很滋润，有一种被甘油笼罩的感觉😂。\n👌🏼不上妆的情况下，几个小时后，还是会觉得脸部事保湿的。\n👌🏼味道清淡，没有各种强烈的味道。\n👌🏼还是用的同样的粉底和蜜粉，不会出现浮粉的现象\n👌🏼包装看似透明玻璃，应该是透明塑料，重量很轻，方便携带\n🎀学生党值得入手🎀\n最后感谢收藏💟和点赞⭐️的小仙女们☀️\n#热门面霜测评"
			}, {
				"user": {
					"image": "https://img.xiaohongshu.com/avatar/58d299d202f37d3d805357bb.jpg@80w_80h_90q_1e_1c_1x.jpg",
					"userid": "57e5ee396a6a691927b75446",
					"discoverys_total": 9,
					"nickname": "小招风耳",
					"id": "57e5ee396a6a691927b75446",
					"fans_total": 65
				},
				"title": "少女心爆棚的凡尔赛玫瑰面膜",
				"image": "http://ci.xiaohongshu.com/fb4855e0-6645-4875-9c9b-7b1213baf027@r_240w_240h.jpg",
				"collect": 10,
				"related_goods_name": "一整张的果冻精华",
				"image_b": "http://ci.xiaohongshu.com/fb4855e0-6645-4875-9c9b-7b1213baf027@r_1280w_1280h.jpg",
				"likes": 32,
				"id": "58d161b2b46c5d60bd28634a",
				"desc": "凡尔赛玫瑰面膜 金色弹力保湿 据说金色是最难买的一款\n小伙伴知道我今天要拍孕妇照 特地提前一天送来给我 并叮嘱我要记得敷面膜 今天妆感才好看[害羞]\n🔻炒鸡少女心的一款包装 拆开后就是一股水蜜桃味 炒鸡好闻！！！\n🔻面膜纸和曼丹 佑天兰差不多厚度 无刺痛感 软软的\n🔻精华啫喱状 介于曼丹与佑天兰之间 精华量适中 拿出来后 袋子里还剩一些\n🔻适合敷15-20分钟 表层精华还很多 但贴近皮肤的那面已经差不多了 不建议敷太久 我敷得忘记时间 结果额头有点泛红\n🔻敷完 最大的感受就是水蜜桃剥皮啦 皮肤水当当 嫩嫩的 肤色有所提亮 但真的不是变白 是因为底层肌肤吃饱了水分 自然透出的那种光泽感！\n🔻拿掉面膜后 接着敷脖子 没有马上洗脸 在按摩的过程中 精华有点化成水状 吸收的很快 并且！没有搓泥的现象 这点我超喜欢[赞R]\n🔻最后洗脸的时候也不会因为精华太厚重而难洗 很棒\n🔻价位相对曼丹和佑天兰高点 只有单片装 没有整盒销售 一片接近40人民币\n综合颜值 味道 吸收程度 和效果 是一款值得回购的面膜[萌萌哒R]"
			}, {
				"user": {
					"image": "https://img.xiaohongshu.com/avatar/58892c4fe9521a66da7493e1.jpg@80w_80h_90q_1e_1c_1x.jpg",
					"userid": "57df13ba50c4b44ec6492af2",
					"discoverys_total": 33,
					"nickname": "兔叽不是软妹子",
					"id": "57df13ba50c4b44ec6492af2",
					"fans_total": 2542
				},
				"title": "SK-II神仙水樱花限定 使用心得以及购买攻略～～",
				"image": "http://ci.xiaohongshu.com/8edd838d-bf0f-4ed7-a79b-e039f77ed98c@r_240w_240h.jpg",
				"collect": 44,
				"related_goods_name": "彻底改变肌肤命运",
				"image_b": "http://ci.xiaohongshu.com/8edd838d-bf0f-4ed7-a79b-e039f77ed98c@r_1280w_1280h.jpg",
				"likes": 51,
				"id": "58d185507836234fde92c03d",
				"desc": "💄三月阳春， 日本樱花🌸也是处在盛开的季节，很多小红薯肯定跑去日本看樱花了，而我只能看着SK-II 带给我的樱花🌸~~~~ SK-II神仙水 是去 日本必购的产品啊，正好男朋友去日本出差了，就让他帮我带了一套回来~~~~\n💄好了，步入正题，#SK-II护肤精华露樱花限量版230ml，送了大红瓶小样15g和30p化妆棉，价格大概是23000日元，还是非常划算的~~~~[讨厌]\n💄来说说我的使用感哈，宝宝我呢是🌸混干🌸，偶尔长痘的肤质，但是近期护肤得当， 用SK-II家的精华露搭配Foreo洗脸仪，痘痘都没怎么出现过了哈哈\n💄神仙水的使用感很好，它的质地轻薄，不粘稠，真的很容易被吸收。很多人有个误区觉得神仙水只适合油皮，因为大家最常听见的就是神仙水祛痘啊收缩毛孔啊~~~\n💄神仙水是有这些功效是没错的啦，但是神仙水还是很保湿的，搭配大红瓶使用，冬天也完全没问题。而且在我使用期间发现痘印也淡化了不少[喜欢]现在用个防晒素颜霜画个眉毛就能出门的感觉太好了~~~\n真的是 you pay for what you get 在年轻的时候真的要好好护肤啊~~~~\n💄以往的经验，很多小红薯会留言问我怎么购买~~~男友是在🌸大阪的高岛屋百货🌸买到的，百货专柜和免税店都可以买，但是我看其他博主的笔记，有些套装好像不一样，具体我也不是很清楚呢，大家可以上网在做点功课哦~~~~~[少女心]\n#一抹樱花粉#我的护肤日常#去日本买什么#SK-IISK-II 护肤精华露(神仙水) "
			}, {
				"user": {
					"image": "https://img.xiaohongshu.com/avatar/58d134d7e9521a7cb566b666.jpg@80w_80h_90q_1e_1c_1x.jpg",
					"userid": "5747923250c4b433020dd8fc",
					"discoverys_total": 2,
					"nickname": "Mistygirl",
					"id": "5747923250c4b433020dd8fc",
					"fans_total": 43
				},
				"title": "安娜柏林眼霜",
				"image": "http://ci.xiaohongshu.com/43ed3a92-7331-4613-ad48-09be2482d095@r_240w_240h.jpg",
				"collect": 107,
				"related_goods_name": "安抚敏感气色好",
				"image_b": "http://ci.xiaohongshu.com/43ed3a92-7331-4613-ad48-09be2482d095@r_1280w_1280h.jpg",
				"likes": 52,
				"id": "58d1347bb46c5d1e4828634a",
				"desc": "这是我的第一支眼\n本来打算买科颜氏牛油果眼霜 但是朋友推荐买这款 说是性价比高\n于是就买了它\n德国崇尚节俭 所以是铝管装（记得很小的时候用的牙膏也是铝管装的😄）\n24岁眼周有轻微小细纹 天生黑眼圈 上眼皮脂肪比较厚内双 下眼容易浮肿\n已经用了半管了 说说用后体验吧😉\n乳黄色 基本上没有气味 不油腻 很滋润 用后细纹基本上没有什么改善 黑眼圈也没有太大改变（毕竟跟着我二十几年了）神奇的地方在于下眼不浮肿了 更神奇的地方是不知道是因为涂眼霜按摩的原因还是眼霜起作用了竟然揉出了双眼皮😆虽然不是很明显 但是之前比以前好多了 已经心满意足了😋\n#适合年轻人的眼霜"
			}, {
				"user": {
					"image": "https://img.xiaohongshu.com/avatar/58d13b9102f37d5c679246e1.jpg@80w_80h_90q_1e_1c_1x.jpg",
					"userid": "5837cf207fc5b81f75290779",
					"discoverys_total": 3,
					"nickname": "Violet*🃏*璐",
					"id": "5837cf207fc5b81f75290779",
					"fans_total": 31
				},
				"title": "26岁以前可以无限回购的好物",
				"image": "http://ci.xiaohongshu.com/946fce80-a132-4093-bb10-4a24a58675d4@r_240w_240h.jpg",
				"collect": 88,
				"related_goods_name": "超润不起脂肪粒",
				"image_b": "http://ci.xiaohongshu.com/946fce80-a132-4093-bb10-4a24a58675d4@r_1280w_1280h.jpg",
				"likes": 48,
				"id": "58d1e98ed5945f796d98378f",
				"desc": "#馥蕾诗馥蕾诗 FRESH 澄糖亮采磨砂面膜#无限回购护肤品#面膜红黑榜科颜氏 Kiehl's 高保湿面霜对于20出头的年轻肌肤，1000元以下可以无限回购的护肤品应该就是这几样了～ 我更偏爱欧美系的护肤品，成分更安全\nfresh家的东西真心一生推，澄糖面膜使用之后皮肤软软的，不仅仅是去角质、更重要的是，洗掉之后还有滋润成分。\n科研室这两个明星产品是经得住考验的，没有花哨的功效，但是保湿很在行。\n贝德玛家除了卸妆液，这款面膜也不错，可以当面霜来用。\n最后，filorga这款面膜，其实还有一个隐藏作用哦。这款抗皱提亮面膜比较白，如果卸妆之后相见心仪的男生，抹一点出去在朦胧的夜色里会很显白～ 不用担心涂粉底液睡觉对皮肤不好啦，涂一层这个就好～"
			}, {
				"user": {
					"image": "https://img.xiaohongshu.com/avatar/5810b9d602f37d4e01dba168.jpg@80w_80h_90q_1e_1c_1x.jpg",
					"userid": "55b38a4ba75c9523793c7b89",
					"discoverys_total": 221,
					"nickname": "YANE",
					"id": "55b38a4ba75c9523793c7b89",
					"fans_total": 5944
				},
				"title": "台湾1028深层洁净卸妆乳200ml",
				"image": "http://ci.xiaohongshu.com/d4eb733b-deac-48c5-b4f3-4e229b815d3c@r_240w_240h.jpg",
				"collect": 43,
				"related_goods_name": "温和卸净不长闭口",
				"image_b": "http://ci.xiaohongshu.com/d4eb733b-deac-48c5-b4f3-4e229b815d3c@r_1280w_1280h.jpg",
				"likes": 28,
				"id": "58d1205cb46c5d3f8128634a",
				"desc": "再来一颗大白菜～\n推荐大家一款性价比超高的卸妆乳哦～女人我最大也有推荐过噢！这款卸妆乳的pH5.5属于弱酸性的，可以温和的卸除彩妆，同时也可以深入毛孔洁净多余的皮脂与污垢噢。还含有8种氨基酸修复元素深层保湿，卸完妆后脸也不会觉得干涩紧绷噢～\n平时一般的妆容用卸妆乳就可以了，浓妆的话还是建议卸妆油噢。眼唇卸妆建议用眼唇专用卸妆产品噢，这里推荐1028眼唇卸妆液。（笔记里有po哦）\n使用方式：\n水洗法\n1.取适量卸妆乳\n2.均匀涂抹于肌肤上\n3.用指腹轻轻打圈溶解彩妆\n4.用大量清水冲洗干净即可\n擦拭法\n1.取适量卸妆乳\n2.均匀涂抹于肌肤上\n3.用指腹轻轻打圈溶解彩妆，不要直接用水冲洗\n4.先用面纸或化妆棉，轻轻顺着肌肤纹理将卸妆乳擦拭掉\n5.用大量清水冲洗即可"
			}, {
				"user": {
					"image": "https://img.xiaohongshu.com/avatar/5870e59ce9521a65fd49a34b.jpg@80w_80h_90q_1e_1c_1x.jpg",
					"userid": "54241bd1d6e4a97a535cf198",
					"discoverys_total": 17,
					"nickname": "ataoego",
					"id": "54241bd1d6e4a97a535cf198",
					"fans_total": 167
				},
				"title": "新西兰超级大碗敏感皮最爱卸妆膏🍻",
				"image": "http://ci.xiaohongshu.com/8b0bd9dd-96e3-45f3-820b-de843326ab5a@r_240w_240h.jpg",
				"collect": 4,
				"related_goods_name": "",
				"image_b": "http://ci.xiaohongshu.com/8b0bd9dd-96e3-45f3-820b-de843326ab5a@r_1280w_1280h.jpg",
				"likes": 4,
				"id": "58d1e590d1d3b971403ce221",
				"desc": "常年在一家代购店代购保健品 然后去年年底我从国外旅游回来额头长了闭口 我问店主mm有没有什么产品去闭口 她给我推荐了一个大白卸妆膏 在新西兰药房有售 对敏感皮很友好 清洁力也很ok 我就买了一罐试试 超大一罐价格才一百多 我混油偏干 这个超级适合我 敷上去有点凉 类似于面霜的质地 卸的干净又滋润 🍭🍭🍭如果妹子们白天只用防晒和隔离，那只需要干手干脸挖一坨大白在脸上按摩1-2分钟，用化妆棉擦掉，然后直接泡沫洁面洗干净即可；如果妹子们白天要上彩妆，比如粉底等等，大白作为卸妆乳是可以卸的干净的，但是，我们追求的是通透质感的肌肤，追求的是完全不会因为卸妆导致闭口和痘痘，那么就推荐大家按照大白——卸妆油（自己的）——泡沫洁面。你会发现真的不一样哦~差不多使用一个月 真的很不一样！皮肤很光滑闭口几乎没有了（当然我也有配合其他产品）值得安利！\n#有哪些好用的卸妆膏"
			}
		]
	},
	"success": true
}